<?xml version="1.0" ?>
<annotation>
<folder>videogrey</folder>
<filename>frame1280.jpg</filename>
<path>D:\360MoveData\Users\DELL\Desktop\spyder_test\videogrey\frame1280.jpg</path>
<source>
    <database>Unknown</database>
</source>
<size>
    <width>960</width>
    <height>540</height>
    <depth>3</depth>
</size>

<segmented>0</segmented>
    <object>
    <name>fish</name>
    <pose>Unspecified</pose>
    <truncated>0</truncated>
    <difficult>0</difficult>
    <bndbox>
        <xmin>66</xmin>
        <ymin>232</ymin>
        <xmax>84</xmax>
        <ymax>284</ymax>
    </bndbox>
</object>
    <object>
    <name>fish</name>
    <pose>Unspecified</pose>
    <truncated>0</truncated>
    <difficult>0</difficult>
    <bndbox>
        <xmin>258</xmin>
        <ymin>174</ymin>
        <xmax>288</xmax>
        <ymax>205</ymax>
    </bndbox>
</object>
    <object>
    <name>fish</name>
    <pose>Unspecified</pose>
    <truncated>0</truncated>
    <difficult>0</difficult>
    <bndbox>
        <xmin>272</xmin>
        <ymin>144</ymin>
        <xmax>316</xmax>
        <ymax>186</ymax>
    </bndbox>
</object>
    <object>
    <name>fish</name>
    <pose>Unspecified</pose>
    <truncated>0</truncated>
    <difficult>0</difficult>
    <bndbox>
        <xmin>236</xmin>
        <ymin>124</ymin>
        <xmax>288</xmax>
        <ymax>148</ymax>
    </bndbox>
</object>
    <object>
    <name>fish</name>
    <pose>Unspecified</pose>
    <truncated>0</truncated>
    <difficult>0</difficult>
    <bndbox>
        <xmin>252</xmin>
        <ymin>28</ymin>
        <xmax>308</xmax>
        <ymax>56</ymax>
    </bndbox>
</object>
    <object>
    <name>fish</name>
    <pose>Unspecified</pose>
    <truncated>0</truncated>
    <difficult>0</difficult>
    <bndbox>
        <xmin>488</xmin>
        <ymin>53</ymin>
        <xmax>529</xmax>
        <ymax>78</ymax>
    </bndbox>
</object>
</annotation>
